PositionData/__init__.py
PositionData/grids.py
PositionData/methane_data.py
PositionData/position_base.py
PositionData/position_data.py
PositionData/trajectory.py
PositionData/wind_data.py
tests/__init__.py
tests/test_methane_data.py
tests/test_position_data.py
tests/test_trajectory.py
tests/test_wind_data.py
tests/test_wind_map.py
PositionData-0.1.11.dist-info/LICENSE
PositionData-0.1.11.dist-info/METADATA
PositionData-0.1.11.dist-info/WHEEL
PositionData-0.1.11.dist-info/top_level.txt
PositionData-0.1.11.dist-info/RECORD
