Metadata-Version: 2.1
Name: PositionData
Version: 0.1.11
Summary: Georeferenced CSV data processing
Home-page: https://github.com/ugcs/positiondata
Author: SPH Engineering
Author-email: ayankelevich@ugcs.com
License: UNKNOWN
Platform: UNKNOWN
Classifier: License :: OSI Approved :: Apache Software License
Classifier: Programming Language :: Python :: 3.9
Classifier: Programming Language :: Python :: 3.10
Classifier: Programming Language :: Python :: 3.11
License-File: LICENSE
Requires-Dist: geopandas
Requires-Dist: geopy
Requires-Dist: haversine
Requires-Dist: numpy
Requires-Dist: pandas
Requires-Dist: pyproj
Requires-Dist: rasterio
Requires-Dist: scipy
Requires-Dist: shapely
Requires-Dist: windrose
